{
  "gitSyncId": "67423c9225b75e709dd59b82_788fe6fd-2dd2-4e31-9c1a-692024f419ff",
  "id": "Page1_JSObject1.myFun2",
  "pluginId": "js-plugin",
  "pluginType": "JS",
  "unpublishedAction": {
    "actionConfiguration": {
      "encodeParamsToggle": true,
      "jsArguments": [],
      "paginationType": "NONE",
      "timeoutInMillisecond": 10000
    },
    "clientSideExecution": true,
    "collectionId": "Page1_JSObject1",
    "confirmBeforeExecute": false,
    "datasource": {
      "isAutoGenerated": false,
      "name": "UNUSED_DATASOURCE",
      "pluginId": "js-plugin"
    },
    "dynamicBindingPathList": [
      {
        "key": "body"
      }
    ],
    "executeOnLoad": false,
    "fullyQualifiedName": "JSObject1.myFun2",
    "name": "myFun2",
    "pageId": "Page1",
    "userSetOnLoad": false
  }
}